devRantSimple/__init__.py
devRantSimple/devRantSimple.py
devRantSimple-2.2.dist-info/METADATA
devRantSimple-2.2.dist-info/RECORD
devRantSimple-2.2.dist-info/WHEEL
devRantSimple-2.2.dist-info/top_level.txt
