Metadata-Version: 2.1
Name: devRantSimple
Version: 2.2
Summary: A simple devRant api wrapper for the lazy people
Home-page: https://github.com/Ewpratten/devRantSimple
Author: Evan Pratten
Author-email: ewpratten@gmail.com
License: MIT
Platform: UNKNOWN
Classifier: Programming Language :: Python :: 3
Classifier: License :: OSI Approved :: MIT License
Classifier: Operating System :: OS Independent
Classifier: Development Status :: 5 - Production/Stable
